notion_md/__init__.py
notion_md/basicblock.py
notion_md/block.py
notion_md/cache.py
notion_md/client_api.py
notion_md/database.py
notion_md/div.py
notion_md/main.py
notion_md/md.py
notion_md/page.py
notion_md/page2md.py
notion_md/time.py
notion_md/ufile.py
notion_md/web.py
notion_md-2.1.1.dist-info/LICENSE
notion_md-2.1.1.dist-info/METADATA
notion_md-2.1.1.dist-info/WHEEL
notion_md-2.1.1.dist-info/entry_points.txt
notion_md-2.1.1.dist-info/top_level.txt
notion_md-2.1.1.dist-info/RECORD
