Metadata-Version: 2.1
Name: notion-md
Version: 2.1.1
Summary: A package for notion2md
Home-page: https://github.com/qxxiao/notion2md
Author: qxxiao
Author-email: 1063064004@qq.com
License: MIT
Platform: all
Classifier: Natural Language :: Chinese (Simplified)
Classifier: License :: OSI Approved :: MIT License
Classifier: Programming Language :: Python :: 3
Classifier: Programming Language :: Python :: 3.8
License-File: LICENSE
Requires-Dist: bs4
Requires-Dist: notion-client
